{
    "total": [
        {
            "id": "1578274342",
            "count": 68
        },
        {
            "id": "100000456845288",
            "count": 13
        },
        {
            "id": "100000773512616",
            "count": 0
        },
        {
            "id": "100005541676195",
            "count": 0
        },
        {
            "id": "100024106605917",
            "count": 0
        },
        {
            "id": "100039441414188",
            "count": 39
        },
        {
            "id": "100040461800609",
            "count": 49
        },
        {
            "id": "100047717079084",
            "count": 0
        },
        {
            "id": "100058361242612",
            "count": 31
        },
        {
            "id": "100061996530766",
            "count": 10
        },
        {
            "id": "100065430669235",
            "count": 3
        },
        {
            "id": "100067731976878",
            "count": 528
        },
        {
            "id": "100068736295301",
            "count": 0
        },
        {
            "id": "100070502703093",
            "count": 6
        },
        {
            "id": "100074030268329",
            "count": 101
        },
        {
            "id": "100076572061509",
            "count": 41
        },
        {
            "id": "100078004367335",
            "count": 68
        },
        {
            "id": "100082145035733",
            "count": 0
        },
        {
            "id": "100082304654927",
            "count": 0
        },
        {
            "id": "100082668132301",
            "count": 162
        },
        {
            "id": "100083244550129",
            "count": 12
        },
        {
            "id": "100083503856164",
            "count": 3
        },
        {
            "id": "100084473846805",
            "count": 0
        },
        {
            "id": "100086086277912",
            "count": 0
        },
        {
            "id": "100086169773068",
            "count": 0
        },
        {
            "id": "100086727461301",
            "count": 0
        },
        {
            "id": "100087946637555",
            "count": 265
        },
        {
            "id": "100088073572553",
            "count": 13
        },
        {
            "id": "100088243110853",
            "count": 0
        },
        {
            "id": "100088283447287",
            "count": 0
        },
        {
            "id": "100088815016051",
            "count": 25
        },
        {
            "id": "100089091826357",
            "count": 4
        },
        {
            "id": "100089199870117",
            "count": 42
        },
        {
            "id": "100089471555219",
            "count": 0
        },
        {
            "id": "100089642890018",
            "count": 0
        },
        {
            "id": "100082453017179",
            "count": 351
        },
        {
            "id": "100047466490461",
            "count": 6
        },
        {
            "id": "100052564392987",
            "count": 14
        },
        {
            "id": "100084248103659",
            "count": 48
        },
        {
            "id": "100090115531745",
            "count": 44
        },
        {
            "id": "100089783986917",
            "count": 26
        },
        {
            "id": "100083186343710",
            "count": 113
        },
        {
            "id": "100074375732881",
            "count": 43
        }
    ],
    "week": [
        {
            "id": "1578274342",
            "count": 68
        },
        {
            "id": "100000456845288",
            "count": 13
        },
        {
            "id": "100000773512616",
            "count": 0
        },
        {
            "id": "100005541676195",
            "count": 0
        },
        {
            "id": "100024106605917",
            "count": 0
        },
        {
            "id": "100039441414188",
            "count": 39
        },
        {
            "id": "100040461800609",
            "count": 49
        },
        {
            "id": "100047717079084",
            "count": 0
        },
        {
            "id": "100058361242612",
            "count": 31
        },
        {
            "id": "100061996530766",
            "count": 10
        },
        {
            "id": "100065430669235",
            "count": 3
        },
        {
            "id": "100067731976878",
            "count": 528
        },
        {
            "id": "100068736295301",
            "count": 0
        },
        {
            "id": "100070502703093",
            "count": 6
        },
        {
            "id": "100074030268329",
            "count": 101
        },
        {
            "id": "100076572061509",
            "count": 41
        },
        {
            "id": "100078004367335",
            "count": 68
        },
        {
            "id": "100082145035733",
            "count": 0
        },
        {
            "id": "100082304654927",
            "count": 0
        },
        {
            "id": "100082668132301",
            "count": 162
        },
        {
            "id": "100083244550129",
            "count": 12
        },
        {
            "id": "100083503856164",
            "count": 3
        },
        {
            "id": "100084473846805",
            "count": 0
        },
        {
            "id": "100086086277912",
            "count": 0
        },
        {
            "id": "100086169773068",
            "count": 0
        },
        {
            "id": "100086727461301",
            "count": 0
        },
        {
            "id": "100087946637555",
            "count": 265
        },
        {
            "id": "100088073572553",
            "count": 13
        },
        {
            "id": "100088243110853",
            "count": 0
        },
        {
            "id": "100088283447287",
            "count": 0
        },
        {
            "id": "100088815016051",
            "count": 25
        },
        {
            "id": "100089091826357",
            "count": 4
        },
        {
            "id": "100089199870117",
            "count": 42
        },
        {
            "id": "100089471555219",
            "count": 0
        },
        {
            "id": "100089642890018",
            "count": 0
        },
        {
            "id": "100082453017179",
            "count": 351
        },
        {
            "id": "100047466490461",
            "count": 6
        },
        {
            "id": "100052564392987",
            "count": 14
        },
        {
            "id": "100084248103659",
            "count": 48
        },
        {
            "id": "100090115531745",
            "count": 44
        },
        {
            "id": "100089783986917",
            "count": 26
        },
        {
            "id": "100083186343710",
            "count": 113
        },
        {
            "id": "100074375732881",
            "count": 43
        }
    ],
    "day": [
        {
            "id": "1578274342",
            "count": 68
        },
        {
            "id": "100000456845288",
            "count": 13
        },
        {
            "id": "100000773512616",
            "count": 0
        },
        {
            "id": "100005541676195",
            "count": 0
        },
        {
            "id": "100024106605917",
            "count": 0
        },
        {
            "id": "100039441414188",
            "count": 39
        },
        {
            "id": "100040461800609",
            "count": 49
        },
        {
            "id": "100047717079084",
            "count": 0
        },
        {
            "id": "100058361242612",
            "count": 31
        },
        {
            "id": "100061996530766",
            "count": 10
        },
        {
            "id": "100065430669235",
            "count": 3
        },
        {
            "id": "100067731976878",
            "count": 528
        },
        {
            "id": "100068736295301",
            "count": 0
        },
        {
            "id": "100070502703093",
            "count": 6
        },
        {
            "id": "100074030268329",
            "count": 101
        },
        {
            "id": "100076572061509",
            "count": 41
        },
        {
            "id": "100078004367335",
            "count": 68
        },
        {
            "id": "100082145035733",
            "count": 0
        },
        {
            "id": "100082304654927",
            "count": 0
        },
        {
            "id": "100082668132301",
            "count": 162
        },
        {
            "id": "100083244550129",
            "count": 12
        },
        {
            "id": "100083503856164",
            "count": 3
        },
        {
            "id": "100084473846805",
            "count": 0
        },
        {
            "id": "100086086277912",
            "count": 0
        },
        {
            "id": "100086169773068",
            "count": 0
        },
        {
            "id": "100086727461301",
            "count": 0
        },
        {
            "id": "100087946637555",
            "count": 265
        },
        {
            "id": "100088073572553",
            "count": 13
        },
        {
            "id": "100088243110853",
            "count": 0
        },
        {
            "id": "100088283447287",
            "count": 0
        },
        {
            "id": "100088815016051",
            "count": 25
        },
        {
            "id": "100089091826357",
            "count": 4
        },
        {
            "id": "100089199870117",
            "count": 42
        },
        {
            "id": "100089471555219",
            "count": 0
        },
        {
            "id": "100089642890018",
            "count": 0
        },
        {
            "id": "100082453017179",
            "count": 351
        },
        {
            "id": "100047466490461",
            "count": 6
        },
        {
            "id": "100052564392987",
            "count": 14
        },
        {
            "id": "100084248103659",
            "count": 48
        },
        {
            "id": "100090115531745",
            "count": 44
        },
        {
            "id": "100089783986917",
            "count": 26
        },
        {
            "id": "100083186343710",
            "count": 113
        },
        {
            "id": "100074375732881",
            "count": 43
        }
    ],
    "time": 3
}