{
    "total": [
        {
            "id": "100001378940139",
            "count": 59
        },
        {
            "id": "100038181249212",
            "count": 3
        },
        {
            "id": "100047493336393",
            "count": 106
        },
        {
            "id": "100048468064779",
            "count": 2
        },
        {
            "id": "100049573252721",
            "count": 0
        },
        {
            "id": "100062837881940",
            "count": 24
        },
        {
            "id": "100067930177504",
            "count": 45
        },
        {
            "id": "100074485740415",
            "count": 0
        },
        {
            "id": "100075363697156",
            "count": 0
        },
        {
            "id": "100078415485674",
            "count": 0
        },
        {
            "id": "100089388276712",
            "count": 0
        }
    ],
    "week": [
        {
            "id": "100001378940139",
            "count": 59
        },
        {
            "id": "100038181249212",
            "count": 3
        },
        {
            "id": "100047493336393",
            "count": 106
        },
        {
            "id": "100048468064779",
            "count": 2
        },
        {
            "id": "100049573252721",
            "count": 0
        },
        {
            "id": "100062837881940",
            "count": 24
        },
        {
            "id": "100067930177504",
            "count": 45
        },
        {
            "id": "100074485740415",
            "count": 0
        },
        {
            "id": "100075363697156",
            "count": 0
        },
        {
            "id": "100078415485674",
            "count": 0
        },
        {
            "id": "100089388276712",
            "count": 0
        }
    ],
    "day": [
        {
            "id": "100001378940139",
            "count": 59
        },
        {
            "id": "100038181249212",
            "count": 3
        },
        {
            "id": "100047493336393",
            "count": 106
        },
        {
            "id": "100048468064779",
            "count": 2
        },
        {
            "id": "100049573252721",
            "count": 0
        },
        {
            "id": "100062837881940",
            "count": 24
        },
        {
            "id": "100067930177504",
            "count": 45
        },
        {
            "id": "100074485740415",
            "count": 0
        },
        {
            "id": "100075363697156",
            "count": 0
        },
        {
            "id": "100078415485674",
            "count": 0
        },
        {
            "id": "100089388276712",
            "count": 0
        }
    ],
    "time": 5
}