{
    "total": [
        {
            "id": "100004057683479",
            "count": 0
        },
        {
            "id": "100004614814018",
            "count": 1
        },
        {
            "id": "100004770604787",
            "count": 0
        },
        {
            "id": "100005803564997",
            "count": 8
        },
        {
            "id": "100006487225297",
            "count": 0
        },
        {
            "id": "100006586483163",
            "count": 5
        },
        {
            "id": "100009729729076",
            "count": 0
        },
        {
            "id": "100009911326245",
            "count": 0
        },
        {
            "id": "100009933487109",
            "count": 0
        },
        {
            "id": "100012156495946",
            "count": 9
        },
        {
            "id": "100013124891406",
            "count": 0
        },
        {
            "id": "100013261502108",
            "count": 0
        },
        {
            "id": "100013827132140",
            "count": 1
        },
        {
            "id": "100013874310075",
            "count": 4
        },
        {
            "id": "100013932645410",
            "count": 0
        },
        {
            "id": "100014654858596",
            "count": 8
        },
        {
            "id": "100015339970458",
            "count": 0
        },
        {
            "id": "100015505358288",
            "count": 0
        },
        {
            "id": "100016716079068",
            "count": 2
        },
        {
            "id": "100024156502523",
            "count": 0
        },
        {
            "id": "100024364020477",
            "count": 0
        },
        {
            "id": "100024467382924",
            "count": 0
        },
        {
            "id": "100025129472726",
            "count": 0
        },
        {
            "id": "100025142810334",
            "count": 0
        },
        {
            "id": "100027184577415",
            "count": 0
        },
        {
            "id": "100027424852981",
            "count": 0
        },
        {
            "id": "100028008248823",
            "count": 0
        },
        {
            "id": "100030368483626",
            "count": 0
        },
        {
            "id": "100036399510367",
            "count": 0
        },
        {
            "id": "100039210859120",
            "count": 0
        },
        {
            "id": "100043363634825",
            "count": 0
        },
        {
            "id": "100043370900597",
            "count": 0
        },
        {
            "id": "100043950729112",
            "count": 0
        },
        {
            "id": "100044014275736",
            "count": 0
        },
        {
            "id": "100046662650245",
            "count": 1
        },
        {
            "id": "100053200981939",
            "count": 1
        },
        {
            "id": "100057289032389",
            "count": 0
        },
        {
            "id": "100058548293549",
            "count": 0
        },
        {
            "id": "100059127109043",
            "count": 0
        },
        {
            "id": "100061306280380",
            "count": 10
        },
        {
            "id": "100063615670741",
            "count": 0
        },
        {
            "id": "100068146547370",
            "count": 0
        },
        {
            "id": "100071066569455",
            "count": 0
        },
        {
            "id": "100074913247768",
            "count": 0
        },
        {
            "id": "100075738532101",
            "count": 0
        },
        {
            "id": "100082074985853",
            "count": 0
        },
        {
            "id": "100083846314629",
            "count": 0
        },
        {
            "id": "100085439900432",
            "count": 0
        },
        {
            "id": "100087246056298",
            "count": 0
        },
        {
            "id": "100087281833070",
            "count": 0
        },
        {
            "id": "100087289807359",
            "count": 0
        },
        {
            "id": "100089810657197",
            "count": 7
        },
        {
            "id": "100021762320148",
            "count": 20
        },
        {
            "id": "100052288294380",
            "count": 1
        },
        {
            "id": "100081332756379",
            "count": 3
        },
        {
            "id": "100059423581967",
            "count": 1
        },
        {
            "id": "100040418270677",
            "count": 3
        }
    ],
    "week": [
        {
            "id": "100004057683479",
            "count": 0
        },
        {
            "id": "100004614814018",
            "count": 1
        },
        {
            "id": "100004770604787",
            "count": 0
        },
        {
            "id": "100005803564997",
            "count": 8
        },
        {
            "id": "100006487225297",
            "count": 0
        },
        {
            "id": "100006586483163",
            "count": 5
        },
        {
            "id": "100009729729076",
            "count": 0
        },
        {
            "id": "100009911326245",
            "count": 0
        },
        {
            "id": "100009933487109",
            "count": 0
        },
        {
            "id": "100012156495946",
            "count": 9
        },
        {
            "id": "100013124891406",
            "count": 0
        },
        {
            "id": "100013261502108",
            "count": 0
        },
        {
            "id": "100013827132140",
            "count": 1
        },
        {
            "id": "100013874310075",
            "count": 4
        },
        {
            "id": "100013932645410",
            "count": 0
        },
        {
            "id": "100014654858596",
            "count": 8
        },
        {
            "id": "100015339970458",
            "count": 0
        },
        {
            "id": "100015505358288",
            "count": 0
        },
        {
            "id": "100016716079068",
            "count": 2
        },
        {
            "id": "100024156502523",
            "count": 0
        },
        {
            "id": "100024364020477",
            "count": 0
        },
        {
            "id": "100024467382924",
            "count": 0
        },
        {
            "id": "100025129472726",
            "count": 0
        },
        {
            "id": "100025142810334",
            "count": 0
        },
        {
            "id": "100027184577415",
            "count": 0
        },
        {
            "id": "100027424852981",
            "count": 0
        },
        {
            "id": "100028008248823",
            "count": 0
        },
        {
            "id": "100030368483626",
            "count": 0
        },
        {
            "id": "100036399510367",
            "count": 0
        },
        {
            "id": "100039210859120",
            "count": 0
        },
        {
            "id": "100043363634825",
            "count": 0
        },
        {
            "id": "100043370900597",
            "count": 0
        },
        {
            "id": "100043950729112",
            "count": 0
        },
        {
            "id": "100044014275736",
            "count": 0
        },
        {
            "id": "100046662650245",
            "count": 1
        },
        {
            "id": "100053200981939",
            "count": 1
        },
        {
            "id": "100057289032389",
            "count": 0
        },
        {
            "id": "100058548293549",
            "count": 0
        },
        {
            "id": "100059127109043",
            "count": 0
        },
        {
            "id": "100061306280380",
            "count": 10
        },
        {
            "id": "100063615670741",
            "count": 0
        },
        {
            "id": "100068146547370",
            "count": 0
        },
        {
            "id": "100071066569455",
            "count": 0
        },
        {
            "id": "100074913247768",
            "count": 0
        },
        {
            "id": "100075738532101",
            "count": 0
        },
        {
            "id": "100082074985853",
            "count": 0
        },
        {
            "id": "100083846314629",
            "count": 0
        },
        {
            "id": "100085439900432",
            "count": 0
        },
        {
            "id": "100087246056298",
            "count": 0
        },
        {
            "id": "100087281833070",
            "count": 0
        },
        {
            "id": "100087289807359",
            "count": 0
        },
        {
            "id": "100089810657197",
            "count": 7
        },
        {
            "id": "100021762320148",
            "count": 20
        },
        {
            "id": "100052288294380",
            "count": 1
        },
        {
            "id": "100081332756379",
            "count": 3
        },
        {
            "id": "100059423581967",
            "count": 1
        },
        {
            "id": "100040418270677",
            "count": 3
        }
    ],
    "day": [
        {
            "id": "100004057683479",
            "count": 0
        },
        {
            "id": "100004614814018",
            "count": 1
        },
        {
            "id": "100004770604787",
            "count": 0
        },
        {
            "id": "100005803564997",
            "count": 8
        },
        {
            "id": "100006487225297",
            "count": 0
        },
        {
            "id": "100006586483163",
            "count": 5
        },
        {
            "id": "100009729729076",
            "count": 0
        },
        {
            "id": "100009911326245",
            "count": 0
        },
        {
            "id": "100009933487109",
            "count": 0
        },
        {
            "id": "100012156495946",
            "count": 9
        },
        {
            "id": "100013124891406",
            "count": 0
        },
        {
            "id": "100013261502108",
            "count": 0
        },
        {
            "id": "100013827132140",
            "count": 1
        },
        {
            "id": "100013874310075",
            "count": 4
        },
        {
            "id": "100013932645410",
            "count": 0
        },
        {
            "id": "100014654858596",
            "count": 8
        },
        {
            "id": "100015339970458",
            "count": 0
        },
        {
            "id": "100015505358288",
            "count": 0
        },
        {
            "id": "100016716079068",
            "count": 2
        },
        {
            "id": "100024156502523",
            "count": 0
        },
        {
            "id": "100024364020477",
            "count": 0
        },
        {
            "id": "100024467382924",
            "count": 0
        },
        {
            "id": "100025129472726",
            "count": 0
        },
        {
            "id": "100025142810334",
            "count": 0
        },
        {
            "id": "100027184577415",
            "count": 0
        },
        {
            "id": "100027424852981",
            "count": 0
        },
        {
            "id": "100028008248823",
            "count": 0
        },
        {
            "id": "100030368483626",
            "count": 0
        },
        {
            "id": "100036399510367",
            "count": 0
        },
        {
            "id": "100039210859120",
            "count": 0
        },
        {
            "id": "100043363634825",
            "count": 0
        },
        {
            "id": "100043370900597",
            "count": 0
        },
        {
            "id": "100043950729112",
            "count": 0
        },
        {
            "id": "100044014275736",
            "count": 0
        },
        {
            "id": "100046662650245",
            "count": 1
        },
        {
            "id": "100053200981939",
            "count": 1
        },
        {
            "id": "100057289032389",
            "count": 0
        },
        {
            "id": "100058548293549",
            "count": 0
        },
        {
            "id": "100059127109043",
            "count": 0
        },
        {
            "id": "100061306280380",
            "count": 10
        },
        {
            "id": "100063615670741",
            "count": 0
        },
        {
            "id": "100068146547370",
            "count": 0
        },
        {
            "id": "100071066569455",
            "count": 0
        },
        {
            "id": "100074913247768",
            "count": 0
        },
        {
            "id": "100075738532101",
            "count": 0
        },
        {
            "id": "100082074985853",
            "count": 0
        },
        {
            "id": "100083846314629",
            "count": 0
        },
        {
            "id": "100085439900432",
            "count": 0
        },
        {
            "id": "100087246056298",
            "count": 0
        },
        {
            "id": "100087281833070",
            "count": 0
        },
        {
            "id": "100087289807359",
            "count": 0
        },
        {
            "id": "100089810657197",
            "count": 7
        },
        {
            "id": "100021762320148",
            "count": 20
        },
        {
            "id": "100052288294380",
            "count": 1
        },
        {
            "id": "100081332756379",
            "count": 3
        },
        {
            "id": "100059423581967",
            "count": 1
        },
        {
            "id": "100040418270677",
            "count": 3
        }
    ],
    "time": 5
}