{
    "total": [
        {
            "id": "100012243095463",
            "count": 0
        },
        {
            "id": "100039697834743",
            "count": 6
        },
        {
            "id": "100040494708143",
            "count": 59
        },
        {
            "id": "100047221011734",
            "count": 0
        },
        {
            "id": "100069991370952",
            "count": 0
        },
        {
            "id": "100076642985613",
            "count": 7
        }
    ],
    "week": [
        {
            "id": "100012243095463",
            "count": 0,
            "name": "Người dùng facebook"
        },
        {
            "id": "100039697834743",
            "count": 0,
            "name": "Người dùng facebook"
        },
        {
            "id": "100040494708143",
            "count": 0,
            "name": "Người dùng facebook"
        },
        {
            "id": "100047221011734",
            "count": 0,
            "name": "Người dùng facebook"
        },
        {
            "id": "100069991370952",
            "count": 0,
            "name": "Người dùng facebook"
        },
        {
            "id": "100076642985613",
            "count": 0,
            "name": "Nguyễn Hoàng Gia Bảo"
        }
    ],
    "day": [
        {
            "id": "100012243095463",
            "count": 0,
            "name": "Người dùng facebook"
        },
        {
            "id": "100039697834743",
            "count": 0,
            "name": "Người dùng facebook"
        },
        {
            "id": "100040494708143",
            "count": 0,
            "name": "Người dùng facebook"
        },
        {
            "id": "100047221011734",
            "count": 0,
            "name": "Người dùng facebook"
        },
        {
            "id": "100069991370952",
            "count": 0,
            "name": "Người dùng facebook"
        },
        {
            "id": "100076642985613",
            "count": 0,
            "name": "Nguyễn Hoàng Gia Bảo"
        }
    ],
    "time": 0
}